flask_paginate/__init__.py
flask_paginate-2024.3.28.dist-info/LICENSE
flask_paginate-2024.3.28.dist-info/METADATA
flask_paginate-2024.3.28.dist-info/WHEEL
flask_paginate-2024.3.28.dist-info/top_level.txt
flask_paginate-2024.3.28.dist-info/RECORD
